<class name="asn1" context="none" lifecycle="none">
    ASN.1 constants.

    <enum name="tag" definition="public">
        <constant name="boolean" value="0x01"/>
        <constant name="integer" value="0x02"/>
        <constant name="bit string" value="0x03"/>
        <constant name="octet string" value="0x04"/>
        <constant name="null" value="0x05"/>
        <constant name="oid" value="0x06"/>
        <constant name="utf8 string" value="0x0C"/>
        <constant name="sequence" value="0x10"/>
        <constant name="set" value="0x11"/>
        <constant name="printable string" value="0x13"/>
        <constant name="t61 string" value="0x14"/>
        <constant name="ia5 string" value="0x16"/>
        <constant name="utc time" value="0x17"/>
        <constant name="generalized time" value="0x18"/>
        <constant name="universal string" value="0x1C"/>
        <constant name="bmp string" value="0x1E"/>
        <constant name="primitive" value="0x00"/>
        <constant name="constructed" value="0x20"/>
        <constant name="context specific" value="0x80"/>
    </enum>
</class>
